retrotype/__init__.py
retrotype/char_maps.py
retrotype/retrotype.py
retrotype/retrotype_cli.py
retro_typein_tools-0.2.4.dist-info/LICENSE
retro_typein_tools-0.2.4.dist-info/METADATA
retro_typein_tools-0.2.4.dist-info/WHEEL
retro_typein_tools-0.2.4.dist-info/entry_points.txt
retro_typein_tools-0.2.4.dist-info/top_level.txt
retro_typein_tools-0.2.4.dist-info/RECORD
