Metadata-Version: 2.1
Name: retro-typein-tools
Version: 0.2.4
Summary: Debuging and conversion tool for 1980s magazine type-in programs
Author-email: Michael Buhidar <mbuhidar@gmail.com>
License: MIT License
Project-URL: Homepage, https://github.com/mbuhidar/retro_typein_tools
Keywords: commodore64,vic20,commodore,atari,compute,ahoy,run,magazine,c64
Classifier: License :: OSI Approved :: MIT License
Classifier: Programming Language :: Python
Classifier: Programming Language :: Python :: 3
Requires-Python: >=3.6
License-File: LICENSE
Provides-Extra: dev
Requires-Dist: flake8 ; extra == 'dev'
Requires-Dist: pytest ; extra == 'dev'
